MANIFEST.in
README.rst
setup.py
allow2/__init__.py
allow2/common.py
allow2/log.py
allow2/pair.py
allow2.egg-info/PKG-INFO
allow2.egg-info/SOURCES.txt
allow2.egg-info/dependency_links.txt
allow2.egg-info/not-zip-safe
allow2.egg-info/requires.txt
allow2.egg-info/top_level.txt