Metadata-Version: 1.1
Name: allow2
Version: 0.3
Summary: OpenSource Parental Freedom Platform
Home-page: http://github.com/Allow2/Allow2python
Author: Allow2
Author-email: ceo@allow2.com
License: UNKNOWN
Download-URL: https://github.com/Allow2/Allow2Python/archive/0.3.tar.gz
Keywords: parental,controls,time,limit
Platform: UNKNOWN
Classifier: Development Status :: 3 - Alpha
Classifier: Programming Language :: Python :: 2.7
Classifier: Topic :: Text Processing :: Linguistic
